arcade_pylon_api/__init__.py
arcade_pylon_api/moar/openapi.json
arcade_pylon_api/moar/pylon.json
arcade_pylon_api/tools/__init__.py
arcade_pylon_api/tools/request_body_schemas.py
arcade_pylon_api/wrapper_tools/CreateAccountActivity.json
arcade_pylon_api/wrapper_tools/CreateAccountHighlight.json
arcade_pylon_api/wrapper_tools/CreateAiResponseForIssue.json
arcade_pylon_api/wrapper_tools/CreateCustomField.json
arcade_pylon_api/wrapper_tools/CreateIssueNote.json
arcade_pylon_api/wrapper_tools/CreateIssueReply.json
arcade_pylon_api/wrapper_tools/CreateIssueThread.json
arcade_pylon_api/wrapper_tools/CreateKnowledgeBaseArticle.json
arcade_pylon_api/wrapper_tools/CreateMilestone.json
arcade_pylon_api/wrapper_tools/CreateNewAccount.json
arcade_pylon_api/wrapper_tools/CreateNewCollection.json
arcade_pylon_api/wrapper_tools/CreateNewContact.json
arcade_pylon_api/wrapper_tools/CreateNewIssue.json
arcade_pylon_api/wrapper_tools/CreateNewProject.json
arcade_pylon_api/wrapper_tools/CreateNewTag.json
arcade_pylon_api/wrapper_tools/CreateNewTeam.json
arcade_pylon_api/wrapper_tools/CreateRouteRedirect.json
arcade_pylon_api/wrapper_tools/CreateTask.json
arcade_pylon_api/wrapper_tools/CreateTrainingDataConfig.json
arcade_pylon_api/wrapper_tools/DeleteAccount.json
arcade_pylon_api/wrapper_tools/DeleteAccountHighlight.json
arcade_pylon_api/wrapper_tools/DeleteArticle.json
arcade_pylon_api/wrapper_tools/DeleteContact.json
arcade_pylon_api/wrapper_tools/DeleteExistingProject.json
arcade_pylon_api/wrapper_tools/DeleteExistingTag.json
arcade_pylon_api/wrapper_tools/DeleteIssue.json
arcade_pylon_api/wrapper_tools/DeleteMilestone.json
arcade_pylon_api/wrapper_tools/DeleteTask.json
arcade_pylon_api/wrapper_tools/DeleteTrainingDataDocuments.json
arcade_pylon_api/wrapper_tools/FetchAllTags.json
arcade_pylon_api/wrapper_tools/FetchTeamList.json
arcade_pylon_api/wrapper_tools/GetAccountInfo.json
arcade_pylon_api/wrapper_tools/GetAccountList.json
arcade_pylon_api/wrapper_tools/GetAllContacts.json
arcade_pylon_api-1.0.0.dist-info/METADATA
arcade_pylon_api-1.0.0.dist-info/WHEEL
arcade_pylon_api-1.0.0.dist-info/entry_points.txt
arcade_pylon_api-1.0.0.dist-info/licenses/LICENSE
arcade_pylon_api-1.0.0.dist-info/RECORD
